{
  "version": "v1",
  "universal": [
    {
      "id": "intent.orient",
      "label": "Orient",
      "slug": "orient",
      "type": "intent",
      "description": "Helps the user locate themselves in the moment. Orientation, grounding, context."
    },
    {
      "id": "intent.return",
      "label": "Return",
      "slug": "return",
      "type": "intent",
      "description": "Brings the user back to centre. A reset, a re-entry, a gentle snap-to-now."
    },
    {
      "id": "intent.choose",
      "label": "Choose",
      "slug": "choose",
      "type": "intent",
      "description": "Creates choice space. Pauses autopilot and opens options."
    },
    {
      "id": "intent.move",
      "label": "Move",
      "slug": "move",
      "type": "intent",
      "description": "Supports action. Micro-step, runnable behaviour, next right move."
    },
    {
      "id": "intent.prove",
      "label": "Prove",
      "slug": "prove",
      "type": "intent",
      "description": "Captures proof/receipt. Consolidates change through evidence the brain trusts."
    },
    {
      "id": "intent.repair",
      "label": "Repair",
      "slug": "repair",
      "type": "intent",
      "description": "Restores connection or integrity. Relational repair, self-repair, boundary repair."
    },
    {
      "id": "intent.reflect",
      "label": "Reflect",
      "slug": "reflect",
      "type": "intent",
      "description": "Meaning-making and insight. Contemplation, integration, perspective shift."
    },
    {
      "id": "tone.calm",
      "label": "Calm",
      "slug": "calm",
      "type": "tone",
      "description": "Soft, quiet, low-cognitive-load. Non-triggering. Minimal urgency."
    },
    {
      "id": "tone.clear",
      "label": "Clear",
      "slug": "clear",
      "type": "tone",
      "description": "Signal-first. Crisp. Precise. Reduces ambiguity."
    },
    {
      "id": "tone.warm",
      "label": "Warm",
      "slug": "warm",
      "type": "tone",
      "description": "Human, compassionate, safe. Belonging-forward."
    },
    {
      "id": "tone.gentle",
      "label": "Gentle",
      "slug": "gentle",
      "type": "tone",
      "description": "Non-demanding. Inviting. Low pressure."
    },
    {
      "id": "tone.strong",
      "label": "Strong",
      "slug": "strong",
      "type": "tone",
      "description": "Grounded authority. Confident. Clean edges. No fluff."
    },
    {
      "id": "context.moment",
      "label": "Moment",
      "slug": "moment",
      "type": "context",
      "description": "Designed for in-the-moment use. Fast. Runnable under real life."
    },
    {
      "id": "context.session",
      "label": "Session",
      "slug": "session",
      "type": "context",
      "description": "Designed to support between-session or clinician workflows. Review, reflection, coherence."
    },
    {
      "id": "context.system",
      "label": "System",
      "slug": "system",
      "type": "context",
      "description": "Designed for organisational continuity. Governance, reliability, defensibility."
    }
  ]
}